Metadata-Version: 2.4
Name: cursofiap-package-CarolinaPessoa
Version: 1.0.0
Summary: Descricao da sua lib cursofiap
Home-page: 
Author: Carolina Pessoa
Author-email: carolinampessoa@hotmail.com
License: MIT
Dynamic: author
Dynamic: author-email
Dynamic: description
Dynamic: description-content-type
Dynamic: license
Dynamic: summary
